sphinx_gitstamp/__init__.py
tests/conftest.py
tests/test_simple.py
tests/roots/test-root/conf.py
sphinx_gitstamp-0.4.0.dist-info/LICENSE
sphinx_gitstamp-0.4.0.dist-info/METADATA
sphinx_gitstamp-0.4.0.dist-info/WHEEL
sphinx_gitstamp-0.4.0.dist-info/top_level.txt
sphinx_gitstamp-0.4.0.dist-info/RECORD
