Metadata-Version: 2.1
Name: sphinx-gitstamp
Version: 0.4.0
Summary: git timestamp generator for Sphinx
Author-email: Jared Dillard <jared.dillard@gmail.com>
Maintainer-email: Jared Dillard <jared.dillard@gmail.com>
License: MIT
Project-URL: download, https://pypi.org/project/sphinx-gitstamp/
Project-URL: source, https://github.com/jdillard/sphinx-gitstamp
Classifier: Framework :: Sphinx :: Extension
Classifier: License :: OSI Approved :: BSD License
Classifier: Programming Language :: Python :: 3.7
Classifier: Programming Language :: Python :: 3.8
Classifier: Programming Language :: Python :: 3.9
Classifier: Programming Language :: Python :: 3.10
Classifier: Programming Language :: Python :: 3.11
Classifier: Topic :: Documentation :: Sphinx
License-File: LICENSE
Requires-Dist: sphinx >=1.2
Requires-Dist: gitpython
